z3c.autoinclude-1.1-py3.11-nspkg.pth
z3c/autoinclude/README.txt
z3c/autoinclude/__init__.py
z3c/autoinclude/api.py
z3c/autoinclude/api.txt
z3c/autoinclude/dependency.py
z3c/autoinclude/dependency.txt
z3c/autoinclude/meta.zcml
z3c/autoinclude/plugin.py
z3c/autoinclude/plugin.txt
z3c/autoinclude/utils.py
z3c/autoinclude/utils.txt
z3c/autoinclude/zcml.py
z3c/autoinclude/tests/__init__.py
z3c/autoinclude/tests/tests.py
z3c/autoinclude/tests/APackage/setup.py
z3c/autoinclude/tests/APackage/a/__init__.py
z3c/autoinclude/tests/APackage/a/configure.zcml
z3c/autoinclude/tests/BCPackage/setup.py
z3c/autoinclude/tests/BCPackage/b/__init__.py
z3c/autoinclude/tests/BCPackage/b/c/__init__.py
z3c/autoinclude/tests/BCPackage/b/c/configure.zcml
z3c/autoinclude/tests/BasePackage/setup.py
z3c/autoinclude/tests/BasePackage/basepackage/__init__.py
z3c/autoinclude/tests/BasePackage/basepackage/configure.zcml
z3c/autoinclude/tests/FooPackage/setup.py
z3c/autoinclude/tests/FooPackage/foo/__init__.py
z3c/autoinclude/tests/FooPackage/foo/configure.zcml
z3c/autoinclude/tests/SRCPackage/setup.py
z3c/autoinclude/tests/SRCPackage/src/funsrc/__init__.py
z3c/autoinclude/tests/SRCPackage/src/funsrc/configure.zcml
z3c/autoinclude/tests/SiblingPackage/setup.py
z3c/autoinclude/tests/SiblingPackage/F/__init__.py
z3c/autoinclude/tests/SiblingPackage/F/G/__init__.py
z3c/autoinclude/tests/SiblingPackage/F/G/meta.zcml
z3c/autoinclude/tests/SiblingPackage/F/H/__init__.py
z3c/autoinclude/tests/SiblingPackage/F/H/configure.zcml
z3c/autoinclude/tests/SiblingPackage/F/H/meta.zcml
z3c/autoinclude/tests/TestDirective/setup.py
z3c/autoinclude/tests/TestDirective/testdirective/__init__.py
z3c/autoinclude/tests/TestDirective/testdirective/meta.zcml
z3c/autoinclude/tests/TestDirective/testdirective/zcml.py
z3c/autoinclude/tests/XYZPackage/setup.py
z3c/autoinclude/tests/XYZPackage/x/__init__.py
z3c/autoinclude/tests/XYZPackage/x/y/__init__.py
z3c/autoinclude/tests/XYZPackage/x/y/z/__init__.py
z3c.autoinclude-1.1.dist-info/LICENSE.rst
z3c.autoinclude-1.1.dist-info/METADATA
z3c.autoinclude-1.1.dist-info/WHEEL
z3c.autoinclude-1.1.dist-info/entry_points.txt
z3c.autoinclude-1.1.dist-info/namespace_packages.txt
z3c.autoinclude-1.1.dist-info/top_level.txt
z3c.autoinclude-1.1.dist-info/RECORD
