Metadata-Version: 2.1
Name: z3c.autoinclude
Version: 1.1
Summary: Automatically include ZCML
Home-page: https://github.com/zopefoundation/z3c.autoinclude
Author: Zope Foundation and Contributors
Author-email: zope-dev@zope.dev
License: ZPL
Keywords: zcml automatic
Classifier: Development Status :: 5 - Production/Stable
Classifier: Framework :: Zope :: 3
Classifier: License :: OSI Approved :: Zope Public License
Classifier: Programming Language :: Python
Classifier: Programming Language :: Python :: 3.9
Classifier: Programming Language :: Python :: 3.10
Classifier: Programming Language :: Python :: 3.11
Classifier: Programming Language :: Python :: 3.12
Classifier: Programming Language :: Python :: 3.13
Classifier: Programming Language :: Python :: Implementation :: CPython
Classifier: Programming Language :: Python :: Implementation :: PyPy
Requires-Python: >=3.9
License-File: LICENSE.rst
Requires-Dist: setuptools
Requires-Dist: zope.dottedname
Requires-Dist: zope.interface
Requires-Dist: zope.configuration
Requires-Dist: zope.schema>=4.2.0
Provides-Extra: test
Requires-Dist: zc.buildout; extra == "test"
Requires-Dist: zope.testing; extra == "test"
